resht/__init__.py
resht/__main__.py
resht/client.py
resht/dbg.py
resht/formatter.py
resht/jsonx.py
resht/shell.py
resht/types.py
resht/usage.py
resht/utils.py
resht-0.9.10.dist-info/licenses/LICENSE
resht-0.9.10.dist-info/METADATA
resht-0.9.10.dist-info/WHEEL
resht-0.9.10.dist-info/entry_points.txt
resht-0.9.10.dist-info/top_level.txt
resht-0.9.10.dist-info/RECORD
