Metadata-Version: 2.4
Name: resht
Version: 0.9.10
Summary: RESTFul HTTP command-line interface and shell
Home-page: https://github.com/jfillmore/resht
Author: Jonny Fillmore
Author-email: git@jkf.im
Requires-Python: >=3.6
License-File: LICENSE
Dynamic: license-file
